labelify/__init__.py
labelify/__main__.py
labelify/utils.py
labelify-0.6.1.dist-info/METADATA
labelify-0.6.1.dist-info/WHEEL
labelify-0.6.1.dist-info/entry_points.txt
labelify-0.6.1.dist-info/licenses/LICENSE
labelify-0.6.1.dist-info/RECORD
