Metadata-Version: 2.4
Name: labelify
Version: 0.6.1
Summary: Analyse an RDF graph to find URI's without human readable labels.
Author-email: Nicholas Car <nick@kurrawong.ai>
License-Expression: BSD-3-Clause
License-File: LICENSE
Requires-Python: >=3.12
Requires-Dist: html5rdf<2,>=1.2.1
Requires-Dist: kurra>=2.0.5
Requires-Dist: sparqlwrapper<3,>=2.0.0
